datastructuresnadh-0.1.0.dist-info/licenses/LICENSE.txt
ds/__init__.py
ds/queues.py
ds/stack.py
ds/linkedlist/__init__.py
ds/linkedlist/dll.py
ds/linkedlist/sll.py
datastructuresnadh-0.1.0.dist-info/METADATA
datastructuresnadh-0.1.0.dist-info/WHEEL
datastructuresnadh-0.1.0.dist-info/top_level.txt
datastructuresnadh-0.1.0.dist-info/RECORD
