Metadata-Version: 2.4
Name: datastructuresnadh
Version: 0.1.0
Summary: Data Structures Implementation by Badhrinadh
Home-page: https://github.com/Badhrinadhgvs/dspy
Author: Badhrinadh
License: MIT
Classifier: Programming Language :: Python :: 3
Classifier: License :: OSI Approved :: MIT License
Classifier: Operating System :: OS Independent
Requires-Python: >=3.8
License-File: LICENSE.txt
Dynamic: license-file
